recaud/__init__.py
recaud/recaud.py
recaud-0.1.4.dist-info/entry_points.txt
recaud-0.1.4.dist-info/WHEEL
recaud-0.1.4.dist-info/METADATA
recaud-0.1.4.dist-info/RECORD
