Metadata-Version: 2.1
Name: recaud
Version: 0.1.4
Summary: 
Author: dkllrjr
Author-email: dg.kllr.jr@gmail.com
Requires-Python: >=3.8,<4.0
Classifier: Programming Language :: Python :: 3
Classifier: Programming Language :: Python :: 3.8
Requires-Dist: pyyaml (>=5.3.1,<6.0.0)
